tarticle_api/__init__.py
tarticle_api/Api.py
tarticle_api-1.0.0.dist-info/WHEEL
tarticle_api-1.0.0.dist-info/METADATA
tarticle_api-1.0.0.dist-info/RECORD
