Metadata-Version: 2.1
Name: tarticle-api
Version: 1.0.0
Summary: Tarticle API
Author: billyoobones
Author-email: tribidpahi@gmail.com
Requires-Python: >=3.8,<4.0
Classifier: Programming Language :: Python :: 3
Classifier: Programming Language :: Python :: 3.8
Classifier: Programming Language :: Python :: 3.9
